FSM/code/fsmcodedetector.v
module codedetector (
    input  wire clk,
    input  wire reset,
    input  wire s, r, g, b,
    output wire a,
    output reg  unlock
);

    localparam [2:0] S0 = 3'b000, //initial state
                     S1 = 3'b001, // s pressed
                     S2 = 3'b010, // s,r pressed
                     S3 = 3'b011, // s,r,b pressed
                     S4 = 3'b100, // s,r,b,g pressed
                     S5 = 3'b101, // success state
                     Locked = 3'b110; // Locked state
    reg [2:0] state, next_state;
    reg[2:0] wrong_button_count; // Counter for wrong button presses
    reg[3:0] timeout_counter; // Counter for timeout mechanism

    // "Any button pressed" flag
    assign a = s | r | g | b;

    // 1. Sequential Block: State Memory (Synchronous Reset)
    always @(posedge clk) begin
        if (reset) begin
            state <= S0; // Reset to initial state
            wrong_button_count <= 0; // Reset wrong button counter
            timeout_counter <= 0; // Reset timeout counter
        end else begin
            // Timeout logic
            if (a) timeout_counter <= 0; // Reset timeout counter on any button press
            else if (state != S0 && state != Locked) begin
                if (timeout_counter >= 8) timeout_counter <= 0;
                else timeout_counter <= timeout_counter + 1;
                end
                else begin
                    timeout_counter <= 0;
                    end
           //  Wrong button counter 
        if (state == S5) wrong_button_count <= 0; // Reset wrong button counter on success
        else if (a && (next_state == S0) && (state != S0) && (state != Locked)) begin
            wrong_button_count <= wrong_button_count + 1;
            end
           // State update
        state <= next_state;
        end
    end
    // 2. Combinational Block: Next State Logic
    always @(*) begin
        // Default assignments to prevent latches
        next_state = state; 
        
        case(state)
            S0: begin
                
                if (s && !r && !g && !b) next_state = S1; // Only advance if EXACTLY 's' is pressed
                else if (a)              next_state = S0; // Any other press resets
            end
            S1: begin
                if (r && !s && !g && !b) next_state = S2;
                else if (s && !r && !g && !b) next_state = S1; 
                else if (a)              next_state = S0;
            end
            S2: begin
                if (b && !s && !r && !g) next_state = S3;
                else if (s && !r && !g && !b) next_state = S1;
                else if (a)              next_state = S0;
            end
            S3: begin
                if (g && !s && !r && !b) next_state = S4;
                else if (s && !r && !g && !b) next_state = S1;
                else if (a)              next_state = S0;
            end
            S4: begin
                if (r && !s && !g && !b) next_state = S5;
                else if (s && !r && !g && !b) next_state = S1;
                else if (a)              next_state = S0;
            end
            S5: begin
                // Wait in success state until another button is pressed
                if (s && !r && !g && !b) next_state = S1;
                else if (a)              next_state = S0;
            end
            Locked: next_state = Locked; // Stay locked indefinitely
            default: next_state = S0;
        endcase
        if (wrong_button_count >= 3) begin
            next_state = Locked; // Transition to locked state after 3 wrong presses
        end
        if (timeout_counter >= 8 && state != S0 && state != Locked)
            next_state = S0; // Reset to initial state on timeout
    end

    // 3. Sequential Block: Registered Output
    always @(posedge clk) begin
        if (reset) begin
            unlock <= 1'b0;
        end else if (state == S5) begin
            unlock <= 1'b1;
        end else if (state == Locked) begin
            unlock <= 1'b0; // Ensure output is low in locked state
        end else begin
            unlock <= 1'b0;
        end
    end
endmodule

FSM/testbench/fsmcodedetector_tb.v
module tb_code_detector;
    reg clk, rst, s, r, g, b;
    wire u, a;

    codedetector uut (.clk(clk), .reset(rst), .s(s), .r(r), .g(g), .b(b), .a(a),.unlock(u));

    initial clk = 0;
    always #5 clk = ~clk;   //clock signal with period of 10 time units

task press(input ps, pr, pg, pb);
        begin
            s=ps; r=pr; g=pg; b=pb;
            @(posedge clk); #1;
            s=0; r=0; g=0; b=0;
            @(posedge clk); #1;
        end
endtask

integer pass_count, fail_count;
initial begin
    $dumpfile("FSM/waveform/fsm_sim.vcd");
    $dumpvars(0, tb_code_detector);
end 
initial begin
        pass_count = 0;
        fail_count = 0;
        rst=1; {s,r,g,b} = 0;
        @(posedge clk); #1; rst=0;
  // Test 1: Correct sequence 
        $display("Test 1: Correct sequence");
        press(1,0,0,0); // s
        press(0,1,0,0); // r
        press(0,0,0,1); // b
        press(0,0,1,0); // g
        press(0,1,0,0); // r
        @(posedge clk); #1;
        if (u==1) begin
            $display("Test 1 PASS");
            pass_count = pass_count + 1;
        end else begin
            $display("Test 1 FAIL: got u=%b", u);
            fail_count = fail_count + 1;
        end

        // Test 2: Lockout after 3 wrong attempts
        $display("Test 2: Lockout after 3 wrong attempts");
        rst=1; @(posedge clk); #1; rst=0;

        press(1,0,0,0); press(0,0,1,0); // wrong — count=1
        press(1,0,0,0); press(0,0,0,1); // wrong — count=2
        press(1,0,0,0); press(0,0,1,0); // wrong — count=3 → LOCKED

        press(1,0,0,0); press(0,1,0,0);
        press(0,0,0,1); press(0,0,1,0);
        press(0,1,0,0);
        @(posedge clk); #1;
        if (u==0) begin
            $display("Test 2 PASS: Locked correctly");
            pass_count = pass_count + 1;
        end else begin
            $display("Test 2 FAIL: got u=%b", u);
            fail_count = fail_count + 1;
        end

        // Test 3: Reset verification
        $display("Test 3: Reset escapes locked state");
        rst=1; @(posedge clk); #1; rst=0;

        press(1,0,0,0); press(0,1,0,0);
        press(0,0,0,1); press(0,0,1,0);
        press(0,1,0,0);
        @(posedge clk); #1;
        if (u==1) begin
            $display("Test 3 PASS: Reset works");
            pass_count = pass_count + 1;
        end else begin
            $display("Test 3 FAIL: got u=%b", u);
            fail_count = fail_count + 1;
        end

        // Results 
        $display("PASSED : %0d", pass_count);
        $display("FAILED : %0d", fail_count);
        if (fail_count==0) $display("ALL TESTS PASSED");
        else               $display("SOME TESTS FAILED");
        #20; $finish;
end
endmodule

FSM/waveform/fsm_sim.vcd
$date
	Sat Mar 28 13:56:08 2026
$end
$version
	Icarus Verilog
$end
$timescale
	1s
$end
$scope module tb_code_detector $end
$var wire 1 ! u $end
$var wire 1 " a $end
$var reg 1 # b $end
$var reg 1 $ clk $end
$var reg 1 % g $end
$var reg 1 & r $end
$var reg 1 ' rst $end
$var reg 1 ( s $end
$var integer 32 ) fail_count [31:0] $end
$var integer 32 * pass_count [31:0] $end
$scope module uut $end
$var wire 1 " a $end
$var wire 1 # b $end
$var wire 1 $ clk $end
$var wire 1 % g $end
$var wire 1 & r $end
$var wire 1 ' reset $end
$var wire 1 ( s $end
$var parameter 3 + Locked $end
$var parameter 3 , S0 $end
$var parameter 3 - S1 $end
$var parameter 3 . S2 $end
$var parameter 3 / S3 $end
$var parameter 3 0 S4 $end
$var parameter 3 1 S5 $end
$var reg 3 2 next_state [2:0] $end
$var reg 3 3 state [2:0] $end
$var reg 4 4 timeout_counter [3:0] $end
$var reg 1 ! unlock $end
$var reg 3 5 wrong_button_count [2:0] $end
$upscope $end
$scope task press $end
$var reg 1 6 pb $end
$var reg 1 7 pg $end
$var reg 1 8 pr $end
$var reg 1 9 ps $end
$upscope $end
$upscope $end
$enddefinitions $end
$comment Show the parameter values. $end
$dumpall
b101 1
b100 0
b11 /
b10 .
b1 -
b0 ,
b110 +
$end
#0
$dumpvars
x9
x8
x7
x6
bx 5
bx 4
bx 3
b0 2
b0 *
b0 )
0(
1'
0&
0%
0$
0#
0"
x!
$end
#5
b0 4
b0 5
b0 3
0!
1$
#6
1"
b1 2
1(
06
07
08
19
0'
#10
0$
#15
b1 3
1$
#16
0"
b1 2
0(
#20
0$
#25
b1 4
1$
#26
1"
b10 2
1&
18
09
#30
0$
#35
b0 2
b10 3
b0 4
1$
#36
0"
b10 2
0&
#40
0$
#45
b1 4
1$
#46
1"
b11 2
1#
16
08
#50
0$
#55
b0 2
b11 3
b0 4
1$
#56
0"
b11 2
0#
#60
0$
#65
b1 4
1$
#66
1"
b100 2
1%
06
17
#70
0$
#75
b0 2
b100 3
b0 4
1$
#76
0"
b100 2
0%
#80
0$
#85
b1 4
1$
#86
1"
b101 2
1&
07
18
#90
0$
#95
b0 2
b101 3
b0 4
1$
#96
0"
b101 2
0&
#100
0$
#105
b1 4
1!
1$
#110
0$
#115
b10 4
1$
#116
1'
b1 *
#120
0$
#125
b0 2
b0 4
b0 3
0!
1$
#126
1"
b1 2
1(
08
19
0'
#130
0$
#135
b1 3
1$
#136
0"
b1 2
0(
#140
0$
#145
b1 4
1$
#146
b0 2
1"
1%
17
09
#150
0$
#155
b0 3
b1 5
b0 4
1$
#156
0"
0%
#160
0$
#165
1$
#166
1"
b1 2
1(
07
19
#170
0$
#175
b1 3
1$
#176
0"
b1 2
0(
#180
0$
#185
b1 4
1$
#186
b0 2
1"
1#
16
09
#190
0$
#195
b0 3
b10 5
b0 4
1$
#196
0"
0#
#200
0$
#205
1$
#206
1"
b1 2
1(
06
19
#210
0$
#215
b1 3
1$
#216
0"
b1 2
0(
#220
0$
#225
b1 4
1$
#226
b0 2
1"
1%
17
09
#230
0$
#235
b110 2
b0 3
b11 5
b0 4
1$
#236
0"
b110 2
0%
#240
0$
#245
b110 3
1$
#246
1"
1(
07
19
#250
0$
#255
1$
#256
0"
0(
#260
0$
#265
1$
#266
1"
1&
18
09
#270
0$
#275
1$
#276
0"
0&
#280
0$
#285
1$
#286
1"
1#
16
08
#290
0$
#295
1$
#296
0"
0#
#300
0$
#305
1$
#306
1"
1%
06
17
#310
0$
#315
1$
#316
0"
0%
#320
0$
#325
1$
#326
1"
1&
07
18
#330
0$
#335
1$
#336
0"
0&
#340
0$
#345
1$
#350
0$
#355
1$
#356
1'
b10 *
#360
0$
#365
b0 2
b0 5
b0 3
1$
#366
1"
b1 2
1(
08
19
0'
#370
0$
#375
b1 3
1$
#376
0"
b1 2
0(
#380
0$
#385
b1 4
1$
#386
1"
b10 2
1&
18
09
#390
0$
#395
b0 2
b10 3
b0 4
1$
#396
0"
b10 2
0&
#400
0$
#405
b1 4
1$
#406
1"
b11 2
1#
16
08
#410
0$
#415
b0 2
b11 3
b0 4
1$
#416
0"
b11 2
0#
#420
0$
#425
b1 4
1$
#426
1"
b100 2
1%
06
17
#430
0$
#435
b0 2
b100 3
b0 4
1$
#436
0"
b100 2
0%
#440
0$
#445
b1 4
1$
#446
1"
b101 2
1&
07
18
#450
0$
#455
b0 2
b101 3
b0 4
1$
#456
0"
b101 2
0&
#460
0$
#465
b1 4
1!
1$
#470
0$
#475
b10 4
1$
#476
b11 *
#480
0$
#485
b11 4
1$
#490
0$
#495
b100 4
1$
